<?xml version="1.0" encoding="utf-8"?>
<!--
- phpMyAdmin XML Dump
- version 3.5.1
- http://www.phpmyadmin.net
-
- Host: co-project
- Generation Time: May 08, 2014 at 04:11 PM
- Server version: 5.1.73
- PHP Version: 5.3.3
-->

<pma_xml_export version="1.0" xmlns:pma="http://www.phpmyadmin.net/some_doc_url/">
    <!--
    - Structure schemas
    -->
    <pma:structure_schemas>
        <pma:database name="group07" collation="utf8_general_ci" charset="utf8">
            <pma:table name="leaderboard">
                CREATE TABLE `leaderboard` (
                  `username` varchar(150) NOT NULL,
                  `points` int(11) NOT NULL
                ) ENGINE=MyISAM DEFAULT CHARSET=utf8;
            </pma:table>
        </pma:database>
    </pma:structure_schemas>

    <!--
    - Database: 'group07'
    -->
    <database name="group07">
        <!-- Table leaderboard -->
        <table name="leaderboard">
            <column name="username">Chocobo</column>
            <column name="points">800</column>
        </table>
        <table name="leaderboard">
            <column name="username">Helix's Warriors</column>
            <column name="points">385</column>
        </table>
        <table name="leaderboard">
            <column name="username">VadersDroids</column>
            <column name="points">4912</column>
        </table>
        <table name="leaderboard">
            <column name="username">Helix's Warriors</column>
            <column name="points">910</column>
        </table>
        <table name="leaderboard">
            <column name="username">The Cereal Killers </column>
            <column name="points">649</column>
        </table>
        <table name="leaderboard">
            <column name="username">VadersDroids</column>
            <column name="points">651</column>
        </table>
        <table name="leaderboard">
            <column name="username">One_Hit_Wonders</column>
            <column name="points">649</column>
        </table>
        <table name="leaderboard">
            <column name="username">GalbadiaTroops</column>
            <column name="points">505</column>
        </table>
        <table name="leaderboard">
            <column name="username">Thunder-Ducks98 </column>
            <column name="points">845</column>
        </table>
        <table name="leaderboard">
            <column name="username">VadersDroids</column>
            <column name="points">698</column>
        </table>
        <table name="leaderboard">
            <column name="username">TeamStarfleet</column>
            <column name="points">1986</column>
        </table>
        <table name="leaderboard">
            <column name="username">Hex010101 </column>
            <column name="points">220</column>
        </table>
        <table name="leaderboard">
            <column name="username">Team Chocobo</column>
            <column name="points">2154</column>
        </table>
        <table name="leaderboard">
            <column name="username">MightyMorphinPowerPutties</column>
            <column name="points">984</column>
        </table>
        <table name="leaderboard">
            <column name="username">Spirit Monsters</column>
            <column name="points">741</column>
        </table>
        <table name="leaderboard">
            <column name="username">AmericanTanks</column>
            <column name="points">637</column>
        </table>
        <table name="leaderboard">
            <column name="username">NewYorkChuckers10</column>
            <column name="points">702</column>
        </table>
        <table name="leaderboard">
            <column name="username">Red Hawks</column>
            <column name="points">875</column>
        </table>
        <table name="leaderboard">
            <column name="username">Rocky Kings</column>
            <column name="points">952</column>
        </table>
        <table name="leaderboard">
            <column name="username">Red Mutants</column>
            <column name="points">874</column>
        </table>
        <table name="leaderboard">
            <column name="username">Spinning Kickers</column>
            <column name="points">598</column>
        </table>
        <table name="leaderboard">
            <column name="username">Eccentric_Egyptians2</column>
            <column name="points">618</column>
        </table>
        <table name="leaderboard">
            <column name="username">American Mafia</column>
            <column name="points">876</column>
        </table>
        <table name="leaderboard">
            <column name="username">VadersDroidsII</column>
            <column name="points">832</column>
        </table>
        <table name="leaderboard">
            <column name="username">Awesome Racers</column>
            <column name="points">543</column>
        </table>
        <table name="leaderboard">
            <column name="username">The Muffin Stuffers</column>
            <column name="points">214</column>
        </table>
        <table name="leaderboard">
            <column name="username">BadIntention</column>
            <column name="points">478</column>
        </table>
        <table name="leaderboard">
            <column name="username">Rollin_Thunder_Titans</column>
            <column name="points">468</column>
        </table>
        <table name="leaderboard">
            <column name="username">Awesome Bandits</column>
            <column name="points">917</column>
        </table>
        <table name="leaderboard">
            <column name="username">Buster McThunderstick</column>
            <column name="points">594</column>
        </table>
        <table name="leaderboard">
            <column name="username">Team Ramrod</column>
            <column name="points">768</column>
        </table>
        <table name="leaderboard">
            <column name="username">Red Planets</column>
            <column name="points">672</column>
        </table>
        <table name="leaderboard">
            <column name="username">Super Heroes In Training</column>
            <column name="points">288</column>
        </table>
        <table name="leaderboard">
            <column name="username">Axis of Ignorance</column>
            <column name="points">310</column>
        </table>
        <table name="leaderboard">
            <column name="username">Shooting Stars</column>
            <column name="points">359</column>
        </table>
        <table name="leaderboard">
            <column name="username">Nunchuk Kid</column>
            <column name="points">397</column>
        </table>
        <table name="leaderboard">
            <column name="username">Haymaker</column>
            <column name="points">341</column>
        </table>
        <table name="leaderboard">
            <column name="username">Shockwave Pirates</column>
            <column name="points">3109</column>
        </table>
        <table name="leaderboard">
            <column name="username">American Mavericks</column>
            <column name="points">421</column>
        </table>
        <table name="leaderboard">
            <column name="username">Awesome Sonics</column>
            <column name="points">485</column>
        </table>
        <table name="leaderboard">
            <column name="username">Scared Hitless</column>
            <column name="points">4778</column>
        </table>
        <table name="leaderboard">
            <column name="username">The Son of Pitches</column>
            <column name="points">452</column>
        </table>
        <table name="leaderboard">
            <column name="username">Soup-A-Stars</column>
            <column name="points">5130</column>
        </table>
        <table name="leaderboard">
            <column name="username">Spinal Tappers</column>
            <column name="points">5731</column>
        </table>
        <table name="leaderboard">
            <column name="username">Space Monkey Mafia</column>
            <column name="points">1280</column>
        </table>
        <table name="leaderboard">
            <column name="username">Nemesis</column>
            <column name="points">1642</column>
        </table>
        <table name="leaderboard">
            <column name="username">X-man</column>
            <column name="points">1674</column>
        </table>
        <table name="leaderboard">
            <column name="username">Wood Chuckers!</column>
            <column name="points">1274</column>
        </table>
        <table name="leaderboard">
            <column name="username">Xtreme Team</column>
            <column name="points">5</column>
        </table>
        <table name="leaderboard">
            <column name="username">Jurassic Sparks</column>
            <column name="points">1000</column>
        </table>
        <table name="leaderboard">
            <column name="username">CaptainPicard</column>
            <column name="points">1100</column>
        </table>
        <table name="leaderboard">
            <column name="username">CaptainKirk</column>
            <column name="points">1098</column>
        </table>
    </database>
</pma_xml_export>
